blocksworld3d/__init__.py
blocksworld3d/blocksworld3d.py
blocksworld3d/main.py
blocksworld3d/manual_control.py
blocksworld3d/utils/__init__.py
blocksworld3d/utils/core.py
blocksworld3d/utils/entity.py
blocksworld3d/utils/math.py
blocksworld3d/utils/objmesh.py
blocksworld3d/utils/opengl.py
blocksworld3d/utils/params.py
blocksworld3d/utils/problems.py
blocksworld3d/utils/utils.py
blocksworld3d/utils/wrappers.py
blocksworld3d/utils/textures/asphalt_1.png
blocksworld3d/utils/textures/brick_wall_1.png
blocksworld3d/utils/textures/concrete_tiles_1.png
blocksworld3d-0.2.3.dist-info/LICENSE
blocksworld3d-0.2.3.dist-info/METADATA
blocksworld3d-0.2.3.dist-info/WHEEL
blocksworld3d-0.2.3.dist-info/top_level.txt
blocksworld3d-0.2.3.dist-info/RECORD
