Metadata-Version: 2.1
Name: blocksworld3d
Version: 0.2.3
Summary: Minimalistic 3D blocksworld environment simulator for reinforcement learning & robotics research.
Home-page: https://github.com/ethanmclark1/blocksworld3d
Author: Ethan Clark
Author-email: eclark715@gmail.com
License: Apache
Keywords: Environment,Agent,RL,Gym,Robotics,3D
Classifier: Development Status :: 4 - Beta
Classifier: Programming Language :: Python :: 3.7
Classifier: Programming Language :: Python :: 3.8
Classifier: Programming Language :: Python :: 3.9
Classifier: Programming Language :: Python :: 3.10
Requires-Python: >=3.7, <3.11
License-File: LICENSE
Requires-Dist: numpy (>=1.18.0)
Requires-Dist: pyglet (==1.5.27)
Requires-Dist: gymnasium (>=0.26.2)
Provides-Extra: testing
Requires-Dist: pytest (==7.0.1) ; extra == 'testing'
Requires-Dist: torch ; extra == 'testing'
